{"web":{"client_id":"555027673344-8qonakae1jbs3bnbpg2pqlb56p1l01ns.apps.googleusercontent.com","project_id":"batu-lms-tracker","auth_uri":"https://accounts.google.com/o/oauth2/auth","token_uri":"https://oauth2.googleapis.com/token","auth_provider_x509_cert_url":"https://www.googleapis.com/oauth2/v1/certs","client_secret":"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","redirect_uris":["https://batu-lms-students-tracker.streamlit.app/","https://www.batu-lms-students-tracker.streamlit.app","https://batu-lms-students-tracker.streamlit.app"]}}
